habu/__init__.py
habu/config.py
habu/cli/__init__.py
habu/cli/beta_cmd_crack_service.py
habu/cli/beta_cmd_dhcp_server.py
habu/cli/beta_cmd_dnsd.py
habu/cli/beta_cmd_file_entropy.py
habu/cli/beta_cmd_firewalk.py
habu/cli/beta_cmd_firewall.py
habu/cli/beta_cmd_https_server.py
habu/cli/beta_cmd_icmp.py
habu/cli/beta_cmd_icmp_redirect.py
habu/cli/beta_cmd_mhr.py
habu/cli/beta_cmd_proxy.py
habu/cli/beta_cmd_slowloris.py
habu/cli/beta_cmd_sniff.py
habu/cli/beta_cmd_tcproxy.py
habu/cli/beta_cmd_tcproxy2.py
habu/cli/beta_cmd_tlsaudit.py
habu/cli/beta_cmd_wafdetect.py
habu/cli/beta_cmd_webheaders.py
habu/cli/beta_cmd_weburls.py
habu/cli/cmd_arp_ping.py
habu/cli/cmd_arp_poison.py
habu/cli/cmd_arp_sniff.py
habu/cli/cmd_asydns.py
habu/cli/cmd_b64.py
habu/cli/cmd_cert_clone.py
habu/cli/cmd_cert_crtsh.py
habu/cli/cmd_cert_names.py
habu/cli/cmd_config_del.py
habu/cli/cmd_config_set.py
habu/cli/cmd_config_show.py
habu/cli/cmd_crack_luhn.py
habu/cli/cmd_crack_snmp.py
habu/cli/cmd_crypto_fernet.py
habu/cli/cmd_crypto_fernet_genkey.py
habu/cli/cmd_crypto_gppref.py
habu/cli/cmd_crypto_hasher.py
habu/cli/cmd_crypto_xor.py
habu/cli/cmd_data_enrich.py
habu/cli/cmd_data_extract_domain.py
habu/cli/cmd_data_extract_email.py
habu/cli/cmd_data_extract_fqdn.py
habu/cli/cmd_data_extract_ipv4.py
habu/cli/cmd_data_filter.py
habu/cli/cmd_data_select.py
habu/cli/cmd_dhcp_discover.py
habu/cli/cmd_dhcp_starvation.py
habu/cli/cmd_dns_lookup_forward.py
habu/cli/cmd_dns_lookup_reverse.py
habu/cli/cmd_eicar.py
habu/cli/cmd_forkbomb.py
habu/cli/cmd_fqdn_finder.py
habu/cli/cmd_gateway_find.py
habu/cli/cmd_host.py
habu/cli/cmd_http_headers.py
habu/cli/cmd_http_options.py
habu/cli/cmd_http_tech.py
habu/cli/cmd_icmp_ping.py
habu/cli/cmd_ip_asn.py
habu/cli/cmd_ip_geolocation.py
habu/cli/cmd_ip_internal.py
habu/cli/cmd_ip_public.py
habu/cli/cmd_karma.py
habu/cli/cmd_karma_bulk.py
habu/cli/cmd_land.py
habu/cli/cmd_nc.py
habu/cli/cmd_net_contest.py
habu/cli/cmd_net_interfaces.py
habu/cli/cmd_nmap_excluded.py
habu-0.1.39.dist-info/LICENSE
habu-0.1.39.dist-info/METADATA
habu-0.1.39.dist-info/WHEEL
habu-0.1.39.dist-info/entry_points.txt
habu-0.1.39.dist-info/top_level.txt
habu-0.1.39.dist-info/RECORD
