Metadata-Version: 2.1
Name: habu
Version: 0.1.39
Summary: Hacking Toolkit
Home-page: https://github.com/fportantier/habu
Author: Fabian Martinez Portantier
Author-email: fabian@portantier.com
License: BSD 3-clause
Keywords: security
Platform: UNKNOWN
Classifier: Environment :: Console
Classifier: Intended Audience :: Developers
Classifier: Intended Audience :: Information Technology
Classifier: Intended Audience :: System Administrators
Classifier: License :: OSI Approved :: BSD License
Classifier: Topic :: Security
Classifier: Topic :: System :: Networking
Classifier: Programming Language :: Python :: 3.0
Classifier: Programming Language :: Python :: 3.8
Requires-Dist: beautifulsoup4
Requires-Dist: click
Requires-Dist: cryptography
Requires-Dist: dnspython
Requires-Dist: ipwhois
Requires-Dist: lxml
Requires-Dist: netifaces
Requires-Dist: pygments
Requires-Dist: python-whois
Requires-Dist: regex
Requires-Dist: requests
Requires-Dist: requests-cache
Requires-Dist: scapy
Requires-Dist: tldextract
Requires-Dist: validators
